kahi_scopus_works/Kahi_scopus_works.py
kahi_scopus_works/__init__.py
kahi_scopus_works/_version.py
Kahi_scopus_works-0.1.3b0.dist-info/LICENSE
Kahi_scopus_works-0.1.3b0.dist-info/METADATA
Kahi_scopus_works-0.1.3b0.dist-info/WHEEL
Kahi_scopus_works-0.1.3b0.dist-info/top_level.txt
Kahi_scopus_works-0.1.3b0.dist-info/RECORD
